[
  {
    "timestamp": "2026-02-25T22:41:55.152Z",
    "local_time": "01:41:55",
    "category": "autobidbot_stage",
    "data": {
      "message": "[01:41:55] Down = 1.000 (Stage 1: <170s)"
    }
  },
  {
    "timestamp": "2026-02-25T22:42:05.288Z",
    "local_time": "01:42:05",
    "category": "autobidbot_stage",
    "data": {
      "message": "[01:42:05] START BIDDING: \"Down\" for 1 at 174s"
    }
  },
  {
    "timestamp": "2026-02-25T22:42:09.326Z",
    "local_time": "01:42:09",
    "category": "user_polymarket_websocket_order",
    "data": {
      "id": "0x3aae628b2b0595ae5066f9f135a5c4e26b22af61a8665f9730ef70e0b50c456d",
      "owner": "974024e9-b35e-a1ca-6eb7-3f9da0e8a0f9",
      "market": "0x4f12515f4a170a3b0e5f0e7b6d5a0120f80d53d745628592f9385ec10543d75e",
      "asset_id": "33223730730772316266777802650928100868286632582792313897478177608089458107398",
      "side": "BUY",
      "order_owner": "974024e9-b35e-a1ca-6eb7-3f9da0e8a0f9",
      "original_size": "6",
      "size_matched": "0",
      "price": "0.99",
      "associate_trades": [],
      "outcome": "Down",
      "type": "PLACEMENT",
      "created_at": "1772059330",
      "expiration": "1772059395",
      "order_type": "GTD",
      "status": "LIVE",
      "maker_address": "0xFe61Da21eBdf55a8916d0e34205F0cf4989505cd",
      "timestamp": "1772059330264",
      "event_type": "order"
    }
  },
  {
    "timestamp": "2026-02-25T22:42:09.771Z",
    "local_time": "01:42:09",
    "category": "autobidbot_buy",
    "data": {
      "message": "[01:42:09] Ответ от placeTestOrder",
      "status": "live",
      "success": true,
      "orderId": "0x3aae628b2b0595ae5066f9f135a5c4e26b22af61a8665f9730ef70e0b50c456d",
      "price": 0.99,
      "size": 6,
      "takingAmount": "",
      "makingAmount": "",
      "errorMsg": "",
      "orderPriceMinTickSize": 0.01
    }
  },
  {
    "timestamp": "2026-02-25T22:42:11.981Z",
    "local_time": "01:42:11",
    "category": "polymarket_handler",
    "data": {
      "message": "Tick size changed to: \"0.001\""
    }
  },
  {
    "timestamp": "2026-02-25T22:42:11.982Z",
    "local_time": "01:42:11",
    "category": "polymarket_handler",
    "data": {
      "message": "Tick size changed to: \"0.001\""
    }
  },
  {
    "timestamp": "2026-02-25T22:42:14.134Z",
    "local_time": "01:42:14",
    "category": "user_polymarket_websocket_order",
    "data": {
      "id": "0x3aae628b2b0595ae5066f9f135a5c4e26b22af61a8665f9730ef70e0b50c456d",
      "owner": "974024e9-b35e-a1ca-6eb7-3f9da0e8a0f9",
      "market": "0x4f12515f4a170a3b0e5f0e7b6d5a0120f80d53d745628592f9385ec10543d75e",
      "asset_id": "33223730730772316266777802650928100868286632582792313897478177608089458107398",
      "side": "BUY",
      "order_owner": "974024e9-b35e-a1ca-6eb7-3f9da0e8a0f9",
      "original_size": "6",
      "size_matched": "0",
      "price": "0.99",
      "associate_trades": [],
      "outcome": "Down",
      "type": "CANCELLATION",
      "created_at": "1772059330",
      "expiration": "1772059395",
      "order_type": "GTD",
      "status": "INVALID",
      "maker_address": "0xFe61Da21eBdf55a8916d0e34205F0cf4989505cd",
      "timestamp": "1772059335070",
      "event_type": "order"
    }
  },
  {
    "timestamp": "2026-02-25T22:42:17.094Z",
    "local_time": "01:42:17",
    "category": "user_polymarket_websocket_order",
    "data": {
      "id": "0x4ab3adf12e398b0017b4dc37884452eaf940697ceda655b71e3eb3405805907c",
      "owner": "974024e9-b35e-a1ca-6eb7-3f9da0e8a0f9",
      "market": "0x4f12515f4a170a3b0e5f0e7b6d5a0120f80d53d745628592f9385ec10543d75e",
      "asset_id": "33223730730772316266777802650928100868286632582792313897478177608089458107398",
      "side": "BUY",
      "order_owner": "974024e9-b35e-a1ca-6eb7-3f9da0e8a0f9",
      "original_size": "6",
      "size_matched": "0",
      "price": "0.98",
      "associate_trades": [],
      "outcome": "Down",
      "type": "PLACEMENT",
      "created_at": "1772059338",
      "expiration": "1772059404",
      "order_type": "GTD",
      "status": "LIVE",
      "maker_address": "0xFe61Da21eBdf55a8916d0e34205F0cf4989505cd",
      "timestamp": "1772059338035",
      "event_type": "order"
    }
  },
  {
    "timestamp": "2026-02-25T22:42:17.245Z",
    "local_time": "01:42:17",
    "category": "order_retry",
    "data": {
      "type": "order_retry",
      "originalOrderId": "0x3aae628b2b0595ae5066f9f135a5c4e26b22af61a8665f9730ef70e0b50c456d",
      "newOrderId": "0x4ab3adf12e398b0017b4dc37884452eaf940697ceda655b71e3eb3405805907c",
      "oldTickSize": 0.01,
      "newTickSize": "0.01",
      "success": true
    }
  },
  {
    "timestamp": "2026-02-25T22:42:24.067Z",
    "local_time": "01:42:24",
    "category": "user_polymarket_websocket_order",
    "data": {
      "id": "0x4ab3adf12e398b0017b4dc37884452eaf940697ceda655b71e3eb3405805907c",
      "owner": "974024e9-b35e-a1ca-6eb7-3f9da0e8a0f9",
      "market": "0x4f12515f4a170a3b0e5f0e7b6d5a0120f80d53d745628592f9385ec10543d75e",
      "asset_id": "33223730730772316266777802650928100868286632582792313897478177608089458107398",
      "side": "BUY",
      "order_owner": "974024e9-b35e-a1ca-6eb7-3f9da0e8a0f9",
      "original_size": "6",
      "size_matched": "0",
      "price": "0.98",
      "associate_trades": [],
      "outcome": "Down",
      "type": "CANCELLATION",
      "created_at": "1772059338",
      "expiration": "1772059404",
      "order_type": "GTD",
      "status": "CANCELED",
      "maker_address": "0xFe61Da21eBdf55a8916d0e34205F0cf4989505cd",
      "timestamp": "1772059345003",
      "event_type": "order"
    }
  },
  {
    "timestamp": "2026-02-25T22:43:00.007Z",
    "local_time": "01:43:00",
    "category": "autobidbot_stage",
    "data": {
      "message": "[01:43:00] Down = 0.999 (Stage 2: <120s)"
    }
  },
  {
    "timestamp": "2026-02-25T22:44:30.251Z",
    "local_time": "01:44:30",
    "category": "autobidbot_stage",
    "data": {
      "message": "[01:44:30] Down = 1.000 (Stage 3: <40s)"
    }
  }
]