[
  {
    "time": "03:15:27",
    "action": "P4 leader Up @ 0.65",
    "P_A": 0.36,
    "P_B": 0.65,
    "Profit_A": -1.53,
    "Profit_B": 0,
    "budgetLeft": 398.47,
    "S_A": 20,
    "S_B": 21.53,
    "hasActiveGTC": false,
    "gridLevels": null
  },
  {
    "time": "03:15:54",
    "action": "Risk Manager: Rescue Down @ 0.35",
    "P_A": 0.35,
    "P_B": 0.67,
    "Profit_A": -35.01,
    "Profit_B": 18.83,
    "budgetLeft": 364.99,
    "S_A": 20,
    "S_B": 73.84,
    "hasActiveGTC": false,
    "gridLevels": null
  },
  {
    "time": "03:16:21",
    "action": "P4 leader Up @ 0.68",
    "P_A": 0.33,
    "P_B": 0.68,
    "Profit_A": -0.2,
    "Profit_B": 0.9,
    "budgetLeft": 347.06,
    "S_A": 72.74000000000001,
    "S_B": 73.84,
    "hasActiveGTC": false,
    "gridLevels": null
  },
  {
    "time": "03:16:49",
    "action": "Risk Manager: Rescue Down @ 0.29",
    "P_A": 0.29,
    "P_B": 0.73,
    "Profit_A": -126.24,
    "Profit_B": 65.82,
    "budgetLeft": 221.02,
    "S_A": 72.74000000000001,
    "S_B": 264.8,
    "hasActiveGTC": false,
    "gridLevels": null
  },
  {
    "time": "03:17:18",
    "action": "Risk Manager: Rescue Down @ 0.14",
    "P_A": 0.14,
    "P_B": 0.88,
    "Profit_A": -126.24,
    "Profit_B": 65.82,
    "budgetLeft": 221.02,
    "S_A": 72.74000000000001,
    "S_B": 264.8,
    "hasActiveGTC": false,
    "gridLevels": null
  },
  {
    "time": "03:17:45",
    "action": "P1 RF via Down @ 0.09",
    "P_A": 0.09,
    "P_B": 0.95,
    "Profit_A": -0.75,
    "Profit_B": 47.07,
    "budgetLeft": 202.27,
    "S_A": 216.98000000000002,
    "S_B": 264.8,
    "hasActiveGTC": false,
    "gridLevels": null
  },
  {
    "time": "03:18:14",
    "action": "risk-free locked",
    "P_A": 0.1,
    "P_B": 0.91,
    "Profit_A": 11.33,
    "Profit_B": 46.3,
    "budgetLeft": 201.5,
    "S_A": 229.83,
    "S_B": 264.8,
    "hasActiveGTC": false,
    "gridLevels": null
  }
]